reduct/__init__.py
reduct-0.1.0.dist-info/WHEEL
reduct-0.1.0.dist-info/entry_points.txt
reduct-0.1.0.dist-info/METADATA
reduct-0.1.0.dist-info/RECORD
