Metadata-Version: 2.3
Name: reduct
Version: 0.1.0
Summary: A tool for reducing information
Author: Dan Davison
Author-email: Dan Davison <dandavison7@gmail.com>
Requires-Python: >=3.13
